positron/__init__.py
positron/django.py
positron/sitespecific.py
positron/static.py
positron/django_templates/app.py.tmpl
positron/django_templates/manage.py.tmpl
positron/django_templates/settings.py.tmpl
positron/django_templates/urls.py.tmpl
positron/django_templates/wsgi.py.tmpl
toga_positron-0.5.2.dist-info/METADATA
toga_positron-0.5.2.dist-info/WHEEL
toga_positron-0.5.2.dist-info/entry_points.txt
toga_positron-0.5.2.dist-info/top_level.txt
toga_positron-0.5.2.dist-info/RECORD
