Metadata-Version: 2.4
Name: toga-positron
Version: 0.5.2
Summary: A Briefcase plugin for generating Positron apps.
License-Expression: BSD-3-Clause
Requires-Dist: briefcase>=0.3.21
